sphinx_hwt/__init__.py
sphinx_hwt/directive_autodoc.py
sphinx_hwt/directive_components.py
sphinx_hwt/directive_interfaces.py
sphinx_hwt/directive_params.py
sphinx_hwt/directive_schematic.py
sphinx_hwt/sphinx_hwt.py
sphinx_hwt/utils.py
sphinx_hwt/html/schematic_viewer.html
sphinx_hwt/html/node_modules/d3/dist/d3.js
sphinx_hwt/html/node_modules/d3-hwschematic/dist/d3-hwschematic.css
sphinx_hwt/html/node_modules/d3-hwschematic/dist/d3-hwschematic.js
sphinx_hwt/html/node_modules/elkjs/lib/elk.bundled.js
sphinx_hwt-2.7.dist-info/LICENSE
sphinx_hwt-2.7.dist-info/METADATA
sphinx_hwt-2.7.dist-info/WHEEL
sphinx_hwt-2.7.dist-info/top_level.txt
sphinx_hwt-2.7.dist-info/RECORD
