Metadata-Version: 2.1
Name: sphinx-hwt
Version: 2.7
Summary: Sphinx extension to produce interactive schematic for hardware written in HWT
Home-page: https://github.com/Nic30/sphinx-hwt
Author: Michal Orsak
Author-email: Nic30original@gmail.com
License: BSD-3-Clause
Keywords: sphinx documentation HWT FPGA hardware VHDL System Verilog schematic wave
Platform: UNKNOWN
Classifier: Development Status :: 4 - Beta
Classifier: Environment :: Plugins
Classifier: Framework :: Sphinx :: Extension
Classifier: Intended Audience :: Developers
Classifier: License :: OSI Approved :: MIT License
Classifier: Natural Language :: English
Classifier: Operating System :: OS Independent
Classifier: Programming Language :: Python :: 3 :: Only
Classifier: Programming Language :: Python :: 3
Classifier: Programming Language :: Python :: 3.6
Classifier: Programming Language :: Python :: 3.7
Classifier: Programming Language :: Python :: 3.8
Classifier: Programming Language :: Python :: 3.9
Classifier: Topic :: Scientific/Engineering :: Electronic Design Automation (EDA)
Classifier: Topic :: System :: Hardware
Classifier: Topic :: Utilities
Classifier: Topic :: Scientific/Engineering :: Visualization
License-File: LICENSE
Requires-Dist: sphinx (>=4.0.2)
Requires-Dist: hwtGraph (>=2.1)
